py_rofi_bus/__init__.py
py_rofi_bus/__init__.pyc
py_rofi_bus/main_dbus_daemon.py
py_rofi_bus/main_dbus_daemon.pyc
py_rofi_bus/__pycache__/__init__.cpython-36.pyc
py_rofi_bus/__pycache__/main_dbus_daemon.cpython-36.pyc
py_rofi_bus/cli/__init__.py
py_rofi_bus/cli/__init__.pyc
py_rofi_bus/cli/application.py
py_rofi_bus/cli/application.pyc
py_rofi_bus/cli/daemon.py
py_rofi_bus/cli/daemon.pyc
py_rofi_bus/cli/__pycache__/__init__.cpython-36.pyc
py_rofi_bus/cli/__pycache__/application.cpython-36.pyc
py_rofi_bus/cli/__pycache__/daemon.cpython-36.pyc
py_rofi_bus/components/__init__.py
py_rofi_bus/components/__init__.pyc
py_rofi_bus/components/config.py
py_rofi_bus/components/config.pyc
py_rofi_bus/components/daemon.py
py_rofi_bus/components/daemon.pyc
py_rofi_bus/components/script.py
py_rofi_bus/components/script.pyc
py_rofi_bus/components/__pycache__/__init__.cpython-36.pyc
py_rofi_bus/components/__pycache__/config.cpython-36.pyc
py_rofi_bus/components/__pycache__/daemon.cpython-36.pyc
py_rofi_bus/components/__pycache__/script.cpython-36.pyc
py_rofi_bus/components/mixins/__init__.py
py_rofi_bus/components/mixins/__init__.pyc
py_rofi_bus/components/mixins/has_config.py
py_rofi_bus/components/mixins/has_config.pyc
py_rofi_bus/components/mixins/has_pid.py
py_rofi_bus/components/mixins/has_pid.pyc
py_rofi_bus/components/mixins/manages_processes.py
py_rofi_bus/components/mixins/manages_processes.pyc
py_rofi_bus/components/mixins/__pycache__/__init__.cpython-36.pyc
py_rofi_bus/components/mixins/__pycache__/has_config.cpython-36.pyc
py_rofi_bus/components/mixins/__pycache__/has_pid.cpython-36.pyc
py_rofi_bus/components/mixins/__pycache__/manages_processes.cpython-36.pyc
py_rofi_bus/dbus/__init__.py
py_rofi_bus/dbus/__init__.pyc
py_rofi_bus/dbus/daemon.py
py_rofi_bus/dbus/daemon.pyc
py_rofi_bus/dbus/__pycache__/__init__.cpython-36.pyc
py_rofi_bus/dbus/__pycache__/daemon.cpython-36.pyc
py_rofi_bus/utils/__init__.py
py_rofi_bus-0.2.0.dist-info/METADATA
py_rofi_bus-0.2.0.dist-info/RECORD
py_rofi_bus-0.2.0.dist-info/WHEEL
py_rofi_bus-0.2.0.dist-info/entry_points.txt
py_rofi_bus-0.2.0.dist-info/top_level.txt
