Metadata-Version: 1.1
Name: py-rofi-bus
Version: 0.2.0
Summary: A DBus extension for rofi
Home-page: https://github.com/thecjharries/py-rofi-bus#readme
Author: CJ Harries
Author-email: cj@wizardsoftheweb.pro
License: ISC
Project-URL: Issue Tracker, https://github.com/thecjharries/py-rofi-bus/issues
Keywords: rofi,xcb
Platform: UNKNOWN
Classifier: Development Status :: 1 - Planning
Classifier: Environment :: Console
Classifier: Environment :: X11 Applications
